<chunk name="Object" index="0">
  <items count="3">
    <item name="GUID" type_name="gh_guid" type_code="9">10d2d1dd-973d-4345-a29e-df5c8456e84b</item>
    <item name="Lib" type_name="gh_guid" type_code="9">d45b0aa7-fa27-4b91-3a40-b9f60d192781</item>
    <item name="Name" type_name="gh_string" type_code="10">Filter top faces</item>
  </items>
  <chunks count="1">
    <chunk name="Container">
      <items count="4">
        <item name="Description" type_name="gh_string" type_code="10">Uses a threshold to detect the faces which their normal are looking upward.</item>
        <item name="InstanceGuid" type_name="gh_guid" type_code="9">56aaa35e-8d69-4aa2-9637-8e981a463485</item>
        <item name="Name" type_name="gh_string" type_code="10">Filter top faces</item>
        <item name="NickName" type_name="gh_string" type_code="10">F.T.F</item>
      </items>
      <chunks count="4">
        <chunk name="Attributes">
          <items count="2">
            <item name="Bounds" type_name="gh_drawing_rectanglef" type_code="35">
              <X>1546</X>
              <Y>1876</Y>
              <W>80</W>
              <H>44</H>
            </item>
            <item name="Pivot" type_name="gh_drawing_pointf" type_code="31">
              <X>1588</X>
              <Y>1898</Y>
            </item>
          </items>
        </chunk>
        <chunk name="param_input" index="0">
          <items count="6">
            <item name="Description" type_name="gh_string" type_code="10">A face with set of constrains for smoothing operation</item>
            <item name="InstanceGuid" type_name="gh_guid" type_code="9">ca8c8a78-a311-4d55-97eb-a870d087ac43</item>
            <item name="Name" type_name="gh_string" type_code="10">Smoothing Face</item>
            <item name="NickName" type_name="gh_string" type_code="10">SF</item>
            <item name="Optional" type_name="gh_bool" type_code="1">false</item>
            <item name="SourceCount" type_name="gh_int32" type_code="3">0</item>
          </items>
          <chunks count="1">
            <chunk name="Attributes">
              <items count="2">
                <item name="Bounds" type_name="gh_drawing_rectanglef" type_code="35">
                  <X>1548</X>
                  <Y>1878</Y>
                  <W>25</W>
                  <H>20</H>
                </item>
                <item name="Pivot" type_name="gh_drawing_pointf" type_code="31">
                  <X>1562</X>
                  <Y>1888</Y>
                </item>
              </items>
            </chunk>
          </chunks>
        </chunk>
        <chunk name="param_input" index="1">
          <items count="7">
            <item name="Description" type_name="gh_string" type_code="10">maximum angle between the face normal and Z axis in degree. default is 30 degree.</item>
            <item name="InstanceGuid" type_name="gh_guid" type_code="9">e94e6301-433f-44a4-ac3a-bbed76344e75</item>
            <item name="Name" type_name="gh_string" type_code="10">Angle threshold</item>
            <item name="NickName" type_name="gh_string" type_code="10">A.T.</item>
            <item name="Optional" type_name="gh_bool" type_code="1">false</item>
            <item name="SourceCount" type_name="gh_int32" type_code="3">0</item>
            <item name="UseDegrees" type_name="gh_bool" type_code="1">false</item>
          </items>
          <chunks count="2">
            <chunk name="Attributes">
              <items count="2">
                <item name="Bounds" type_name="gh_drawing_rectanglef" type_code="35">
                  <X>1548</X>
                  <Y>1898</Y>
                  <W>25</W>
                  <H>20</H>
                </item>
                <item name="Pivot" type_name="gh_drawing_pointf" type_code="31">
                  <X>1562</X>
                  <Y>1908</Y>
                </item>
              </items>
            </chunk>
            <chunk name="PersistentData">
              <items count="1">
                <item name="Count" type_name="gh_int32" type_code="3">1</item>
              </items>
              <chunks count="1">
                <chunk name="Branch" index="0">
                  <items count="2">
                    <item name="Count" type_name="gh_int32" type_code="3">1</item>
                    <item name="Path" type_name="gh_string" type_code="10">{0}</item>
                  </items>
                  <chunks count="1">
                    <chunk name="Item" index="0">
                      <items count="1">
                        <item name="number" type_name="gh_double" type_code="6">30</item>
                      </items>
                    </chunk>
                  </chunks>
                </chunk>
              </chunks>
            </chunk>
          </chunks>
        </chunk>
        <chunk name="param_output" index="0">
          <items count="6">
            <item name="Description" type_name="gh_string" type_code="10">A face with set of constrains for smoothing operation</item>
            <item name="InstanceGuid" type_name="gh_guid" type_code="9">d67f064c-09a3-41d1-976b-95248451a587</item>
            <item name="Name" type_name="gh_string" type_code="10">Smoothing Face</item>
            <item name="NickName" type_name="gh_string" type_code="10">SF</item>
            <item name="Optional" type_name="gh_bool" type_code="1">false</item>
            <item name="SourceCount" type_name="gh_int32" type_code="3">0</item>
          </items>
          <chunks count="1">
            <chunk name="Attributes">
              <items count="2">
                <item name="Bounds" type_name="gh_drawing_rectanglef" type_code="35">
                  <X>1603</X>
                  <Y>1878</Y>
                  <W>21</W>
                  <H>40</H>
                </item>
                <item name="Pivot" type_name="gh_drawing_pointf" type_code="31">
                  <X>1613.5</X>
                  <Y>1898</Y>
                </item>
              </items>
            </chunk>
          </chunks>
        </chunk>
      </chunks>
    </chunk>
  </chunks>
</chunk>