<chunk name="Object" index="0">
  <items count="2">
    <item name="GUID" type_name="gh_guid" type_code="9">79aa7f47-397c-4d3f-9761-aaf421bb7f5f</item>
    <item name="Name" type_name="gh_string" type_code="10">Domain Box</item>
  </items>
  <chunks count="1">
    <chunk name="Container">
      <items count="5">
        <item name="Description" type_name="gh_string" type_code="10">Create a box defined by a base plane and size domains.</item>
        <item name="Hidden" type_name="gh_bool" type_code="1">true</item>
        <item name="InstanceGuid" type_name="gh_guid" type_code="9">ade49fba-7b10-4e13-997e-4206b36fe12f</item>
        <item name="Name" type_name="gh_string" type_code="10">Domain Box</item>
        <item name="NickName" type_name="gh_string" type_code="10">Box</item>
      </items>
      <chunks count="6">
        <chunk name="Attributes">
          <items count="2">
            <item name="Bounds" type_name="gh_drawing_rectanglef" type_code="35">
              <X>937</X>
              <Y>1610</Y>
              <W>64</W>
              <H>84</H>
            </item>
            <item name="Pivot" type_name="gh_drawing_pointf" type_code="31">
              <X>968</X>
              <Y>1652</Y>
            </item>
          </items>
        </chunk>
        <chunk name="param_input" index="0">
          <items count="6">
            <item name="Description" type_name="gh_string" type_code="10">Base plane</item>
            <item name="InstanceGuid" type_name="gh_guid" type_code="9">223b7ae1-4be2-45eb-8963-b9608db1d04b</item>
            <item name="Name" type_name="gh_string" type_code="10">Base</item>
            <item name="NickName" type_name="gh_string" type_code="10">B</item>
            <item name="Optional" type_name="gh_bool" type_code="1">false</item>
            <item name="SourceCount" type_name="gh_int32" type_code="3">0</item>
          </items>
          <chunks count="2">
            <chunk name="Attributes">
              <items count="2">
                <item name="Bounds" type_name="gh_drawing_rectanglef" type_code="35">
                  <X>939</X>
                  <Y>1612</Y>
                  <W>14</W>
                  <H>20</H>
                </item>
                <item name="Pivot" type_name="gh_drawing_pointf" type_code="31">
                  <X>947.5</X>
                  <Y>1622</Y>
                </item>
              </items>
            </chunk>
            <chunk name="PersistentData">
              <items count="1">
                <item name="Count" type_name="gh_int32" type_code="3">1</item>
              </items>
              <chunks count="1">
                <chunk name="Branch" index="0">
                  <items count="2">
                    <item name="Count" type_name="gh_int32" type_code="3">1</item>
                    <item name="Path" type_name="gh_string" type_code="10">{0}</item>
                  </items>
                  <chunks count="1">
                    <chunk name="Item" index="0">
                      <items count="1">
                        <item name="plane" type_name="gh_plane" type_code="72">
                          <Ox>0</Ox>
                          <Oy>0</Oy>
                          <Oz>0</Oz>
                          <Xx>1</Xx>
                          <Xy>0</Xy>
                          <Xz>0</Xz>
                          <Yx>0</Yx>
                          <Yy>1</Yy>
                          <Yz>0</Yz>
                        </item>
                      </items>
                    </chunk>
                  </chunks>
                </chunk>
              </chunks>
            </chunk>
          </chunks>
        </chunk>
        <chunk name="param_input" index="1">
          <items count="7">
            <item name="Description" type_name="gh_string" type_code="10">Domain of the box in the {x} direction.</item>
            <item name="InstanceGuid" type_name="gh_guid" type_code="9">1110142c-17b7-4214-9c33-8ed16229c799</item>
            <item name="Name" type_name="gh_string" type_code="10">X</item>
            <item name="NickName" type_name="gh_string" type_code="10">X</item>
            <item name="Optional" type_name="gh_bool" type_code="1">false</item>
            <item name="Source" index="0" type_name="gh_guid" type_code="9">977e8e49-a42a-459b-9c4e-0039f64e9cd7</item>
            <item name="SourceCount" type_name="gh_int32" type_code="3">1</item>
          </items>
          <chunks count="2">
            <chunk name="Attributes">
              <items count="2">
                <item name="Bounds" type_name="gh_drawing_rectanglef" type_code="35">
                  <X>939</X>
                  <Y>1632</Y>
                  <W>14</W>
                  <H>20</H>
                </item>
                <item name="Pivot" type_name="gh_drawing_pointf" type_code="31">
                  <X>947.5</X>
                  <Y>1642</Y>
                </item>
              </items>
            </chunk>
            <chunk name="PersistentData">
              <items count="1">
                <item name="Count" type_name="gh_int32" type_code="3">1</item>
              </items>
              <chunks count="1">
                <chunk name="Branch" index="0">
                  <items count="2">
                    <item name="Count" type_name="gh_int32" type_code="3">1</item>
                    <item name="Path" type_name="gh_string" type_code="10">{0}</item>
                  </items>
                  <chunks count="1">
                    <chunk name="Item" index="0">
                      <items count="1">
                        <item name="Interval" type_name="gh_interval1d" type_code="60">
                          <A>-2</A>
                          <B>2</B>
                        </item>
                      </items>
                    </chunk>
                  </chunks>
                </chunk>
              </chunks>
            </chunk>
          </chunks>
        </chunk>
        <chunk name="param_input" index="2">
          <items count="7">
            <item name="Description" type_name="gh_string" type_code="10">Domain of the box in the {y} direction.</item>
            <item name="InstanceGuid" type_name="gh_guid" type_code="9">f4ba7f95-43fa-4349-8174-4485b4d8cef1</item>
            <item name="Name" type_name="gh_string" type_code="10">Y</item>
            <item name="NickName" type_name="gh_string" type_code="10">Y</item>
            <item name="Optional" type_name="gh_bool" type_code="1">false</item>
            <item name="Source" index="0" type_name="gh_guid" type_code="9">977e8e49-a42a-459b-9c4e-0039f64e9cd7</item>
            <item name="SourceCount" type_name="gh_int32" type_code="3">1</item>
          </items>
          <chunks count="2">
            <chunk name="Attributes">
              <items count="2">
                <item name="Bounds" type_name="gh_drawing_rectanglef" type_code="35">
                  <X>939</X>
                  <Y>1652</Y>
                  <W>14</W>
                  <H>20</H>
                </item>
                <item name="Pivot" type_name="gh_drawing_pointf" type_code="31">
                  <X>947.5</X>
                  <Y>1662</Y>
                </item>
              </items>
            </chunk>
            <chunk name="PersistentData">
              <items count="1">
                <item name="Count" type_name="gh_int32" type_code="3">1</item>
              </items>
              <chunks count="1">
                <chunk name="Branch" index="0">
                  <items count="2">
                    <item name="Count" type_name="gh_int32" type_code="3">1</item>
                    <item name="Path" type_name="gh_string" type_code="10">{0}</item>
                  </items>
                  <chunks count="1">
                    <chunk name="Item" index="0">
                      <items count="1">
                        <item name="Interval" type_name="gh_interval1d" type_code="60">
                          <A>-0.5</A>
                          <B>0.5</B>
                        </item>
                      </items>
                    </chunk>
                  </chunks>
                </chunk>
              </chunks>
            </chunk>
          </chunks>
        </chunk>
        <chunk name="param_input" index="3">
          <items count="7">
            <item name="Description" type_name="gh_string" type_code="10">Domain of the box in the {z} direction.</item>
            <item name="InstanceGuid" type_name="gh_guid" type_code="9">fe232d37-2f92-4dd8-9857-ecc8a8158b94</item>
            <item name="Name" type_name="gh_string" type_code="10">Z</item>
            <item name="NickName" type_name="gh_string" type_code="10">Z</item>
            <item name="Optional" type_name="gh_bool" type_code="1">false</item>
            <item name="Source" index="0" type_name="gh_guid" type_code="9">6587c11b-44df-4ed8-b006-41b49bf2f340</item>
            <item name="SourceCount" type_name="gh_int32" type_code="3">1</item>
          </items>
          <chunks count="2">
            <chunk name="Attributes">
              <items count="2">
                <item name="Bounds" type_name="gh_drawing_rectanglef" type_code="35">
                  <X>939</X>
                  <Y>1672</Y>
                  <W>14</W>
                  <H>20</H>
                </item>
                <item name="Pivot" type_name="gh_drawing_pointf" type_code="31">
                  <X>947.5</X>
                  <Y>1682</Y>
                </item>
              </items>
            </chunk>
            <chunk name="PersistentData">
              <items count="1">
                <item name="Count" type_name="gh_int32" type_code="3">1</item>
              </items>
              <chunks count="1">
                <chunk name="Branch" index="0">
                  <items count="2">
                    <item name="Count" type_name="gh_int32" type_code="3">1</item>
                    <item name="Path" type_name="gh_string" type_code="10">{0}</item>
                  </items>
                  <chunks count="1">
                    <chunk name="Item" index="0">
                      <items count="1">
                        <item name="Interval" type_name="gh_interval1d" type_code="60">
                          <A>0</A>
                          <B>0.25</B>
                        </item>
                      </items>
                    </chunk>
                  </chunks>
                </chunk>
              </chunks>
            </chunk>
          </chunks>
        </chunk>
        <chunk name="param_output" index="0">
          <items count="6">
            <item name="Description" type_name="gh_string" type_code="10">Resulting box</item>
            <item name="InstanceGuid" type_name="gh_guid" type_code="9">e1714ce8-ed4f-46c5-9bd1-7cb1e550df70</item>
            <item name="Name" type_name="gh_string" type_code="10">Box</item>
            <item name="NickName" type_name="gh_string" type_code="10">B</item>
            <item name="Optional" type_name="gh_bool" type_code="1">false</item>
            <item name="SourceCount" type_name="gh_int32" type_code="3">0</item>
          </items>
          <chunks count="1">
            <chunk name="Attributes">
              <items count="2">
                <item name="Bounds" type_name="gh_drawing_rectanglef" type_code="35">
                  <X>983</X>
                  <Y>1612</Y>
                  <W>16</W>
                  <H>80</H>
                </item>
                <item name="Pivot" type_name="gh_drawing_pointf" type_code="31">
                  <X>991</X>
                  <Y>1652</Y>
                </item>
              </items>
            </chunk>
          </chunks>
        </chunk>
      </chunks>
    </chunk>
  </chunks>
</chunk>